{"type": "Feature", "id": 12517732, "geometry": {"type": "Point", "coordinates": [54.458981, 24.422991]}, "properties": {"woe:id": 12517732, "woe:parent_id": 1940330, "woe:name": "Bateen Airport", "woe:placetype": 14, "woe:placetype_name": "Airport", "woe:lang": "ENG", "iso:country": "AE", "meta:provider": ["geoplanet:7.3.1", "geoplanet:7.3.2", "geoplanet:7.4.0", "geoplanet:7.4.1", "geoplanet:7.5.1", "geoplanet:7.5.2", "geoplanet:7.6.0", "geoplanet:7.8.1", "geoplanet:7.9.0", "geoplanet:7.10.0", "geoplanet:8.0.0", "woeplanet:8.0.0"], "meta:indexed": "2020-08-20T20:52:00.508615", "woe:alias_ENG_V": ["Al Bateen", "Al Bateen Airport", "AZI Airport", "Bateen", "AZI"], "meta:updated": "2020-10-14T11:28:20.288267", "woe:hierarchy": {"continent": 24865671, "country": 23424738, "town": 0, "planet": 1, "county": 55922608, "suburb": 0, "state": 2347109, "region": 0, "localadmin": 0}, "woe:timezone_id": 28350824, "woe:hash": "thqdznpf4px2", "woe:centroid": [54.458981, 24.422991], "geom:latitude": 24.422991, "geom:longitude": 54.458981, "geom:hash": "thqdznpf4px2", "woe:latitude": 24.422991, "geom:centroid": [54.458981, 24.422991], "woe:longitude": 54.458981, "woe:repo": "woeplanet-airport-ae", "geom:area": 0.0, "woe:scale": 19}}